beyondmimic/__init__.py
beyondmimic/beyondmimic.cpython-310-aarch64-linux-gnu.so
beyondmimic/beyondmimic.cpython-310-x86_64-linux-gnu.so
lcm_types/__init__.py
lcm_types/arm_action_lcmt.py
lcm_types/arm_action_q_t.py
lcm_types/arm_lcm_q_t
lcm_types/arm_lcmt.lcm
lcm_types/body_control_data_lcmt.lcm
lcm_types/body_control_data_lcmt.py
lcm_types/body_record_lcmt.lcm
lcm_types/body_record_lcmt.py
lcm_types/command_lcmt.hpp
lcm_types/command_lcmt.lcm
lcm_types/command_lcmt.py
lcm_types/hand_action_lcmt.py
lcm_types/hand_lcmt.lcm
lcm_types/key_control.lcm
lcm_types/key_control.py
lcm_types/pd_tau_targets_lcmt.lcm
lcm_types/pd_tau_targets_lcmt.py
lcm_types/rc_command_lcmt.lcm
lcm_types/rc_command_lcmt.py
lcm_types/signal_lcmt.lcm
lcm_types/state_estimator_lcmt.lcm
lcm_types/state_estimator_lcmt.py
utils/__init__.py
utils/motion_lib.py
utils/torch_utils.py
beyondmimic-0.2.9.dist-info/METADATA
beyondmimic-0.2.9.dist-info/WHEEL
beyondmimic-0.2.9.dist-info/top_level.txt
beyondmimic-0.2.9.dist-info/RECORD
